psauron/TCN_model.py
psauron/__init__.py
psauron/psauron.py
psauron/data/__init__.py
psauron/data/model_state_dict.pt
psauron-1.0.8.dist-info/licenses/LICENSE.txt
tests/__init__.py
tests/test_eye_of_psauron.py
tests/test_load_model.py
tests/test_reverse_complement.py
psauron-1.0.8.dist-info/METADATA
psauron-1.0.8.dist-info/WHEEL
psauron-1.0.8.dist-info/entry_points.txt
psauron-1.0.8.dist-info/top_level.txt
psauron-1.0.8.dist-info/RECORD
