Metadata-Version: 2.4
Name: psauron
Version: 1.0.8
Summary: A tool to assess protein coding gene annotation
Home-page: https://github.com/Markusjsommer/psauron
Author: markus
Author-email: markusjsommer@gmail.com
License: MIT
Classifier: License :: OSI Approved :: MIT License
Classifier: Programming Language :: Python :: 3.11
Classifier: Operating System :: POSIX :: Linux
Classifier: Operating System :: MacOS :: MacOS X
Requires-Python: >=3.9, <3.13
License-File: LICENSE.txt
Requires-Dist: torch>=2.1.2
Requires-Dist: torchvision>=0.16.2
Requires-Dist: torchaudio>=2.1.2
Requires-Dist: typing-extensions>=4.9.0
Requires-Dist: tqdm>=4.66.1
Requires-Dist: scipy>=1.10.1
Requires-Dist: numpy<2,>=1.24.4
Requires-Dist: pandas
Requires-Dist: setuptools<81
Provides-Extra: dev
Requires-Dist: pytest>=7.0; extra == "dev"
Requires-Dist: twine>=4.0.2; extra == "dev"
Requires-Dist: pytest-cov>=4.0; extra == "dev"
Requires-Dist: wheel; extra == "dev"
Dynamic: author
Dynamic: author-email
Dynamic: classifier
Dynamic: description
Dynamic: description-content-type
Dynamic: home-page
Dynamic: license
Dynamic: license-file
Dynamic: provides-extra
Dynamic: requires-dist
Dynamic: requires-python
Dynamic: summary
